{
  "dockbarproperties": [
    {
      "name": "height",
      "type": "string",
      "default": "",
      "description": "height of dockbar."
    }
  ],
  "dockbaritemproperties": [
    {
      "name": "title",
      "type": "string",
      "default": "",
      "description": "title of dockbar item"
    },
    {
      "name": "width",
      "type": "string",
      "default": "",
      "description": "width of dockbar item"
    },
    {
      "name": "imagePath",
      "type": "string",
      "default": "",
      "description": "Specifies the URL of an image.this is attribute use only for images"
    },
    {
      "name": "icon",
      "type": "string",
      "default": "",
      "description": "icon name Material Example: icon='home'  Fontawesome Example: icon='fa fa-address-book'"
    },
    {
      "name": "mdbClass",
      "type": "string",
      "default": "",
      "description": "this attribute use for only material icons.Material Example:mdbClass='material-icons'"
    }
  ]
}
